{
  "metadata": {
    "generated_at": "2026-07-04T17:07:44Z"
  },
  "summary": {
    "file_count": 4,
    "node_count": 4,
    "edge_count": 4,
    "cycle_count": 1
  },
  "statistics": {
    "class_count": 2,
    "function_count": 3,
    "total_internal_dependencies": 4,
    "total_external_dependencies": 3
  },
  "graph": {
    "nodes": [
      "myapp/__init__.py",
      "myapp/auth.py",
      "myapp/models.py",
      "myapp/utils.py"
    ],
    "edges": [
      {
        "source": "myapp/auth.py",
        "target": "myapp/models.py",
        "type": "imports"
      },
      {
        "source": "myapp/auth.py",
        "target": "myapp/utils.py",
        "type": "imports"
      },
      {
        "source": "myapp/models.py",
        "target": "myapp/utils.py",
        "type": "imports"
      },
      {
        "source": "myapp/utils.py",
        "target": "myapp/models.py",
        "type": "imports"
      }
    ]
  },
  "analysis": {
    "cycles": {
      "has_cycles": true,
      "cycle_count": 1,
      "cycles": [
        {
          "nodes": [
            "myapp/models.py",
            "myapp/utils.py"
          ],
          "length": 2,
          "edges": [
            {
              "source": "myapp/models.py",
              "target": "myapp/utils.py",
              "type": "imports"
            },
            {
              "source": "myapp/utils.py",
              "target": "myapp/models.py",
              "type": "imports"
            }
          ]
        }
      ]
    },
    "scores": [
      {
        "file_path": "myapp/models.py",
        "pagerank": 0.452380773567559,
        "betweenness": 0.0,
        "criticality": 0.6,
        "in_degree": 2,
        "out_degree": 1
      },
      {
        "file_path": "myapp/utils.py",
        "pagerank": 0.452380773567559,
        "betweenness": 0.0,
        "criticality": 0.6,
        "in_degree": 2,
        "out_degree": 1
      },
      {
        "file_path": "myapp/__init__.py",
        "pagerank": 0.04761922643244094,
        "betweenness": 0.0,
        "criticality": 0.0,
        "in_degree": 0,
        "out_degree": 0
      },
      {
        "file_path": "myapp/auth.py",
        "pagerank": 0.04761922643244094,
        "betweenness": 0.0,
        "criticality": 0.0,
        "in_degree": 0,
        "out_degree": 2
      }
    ]
  }
}
